relay_mesos
