Metadata-Version: 1.0
Name: relay.mesos
Version: 0.0.12
Summary: A plugin for Relay that lets you run Relay on Mesos to auto-scale the number of concurrently running instances of a bash command.  Generally, Relay lets you minimize the difference between a metric and a target timeseries. 
